pyCellPhenoX/CellPhenoX.py
pyCellPhenoX/__init__.py
pyCellPhenoX/marker_discovery.py
pyCellPhenoX/neighborhoodAbundanceMatrix.py
pyCellPhenoX/nonnegativeMatrixFactorization.py
pyCellPhenoX/plot_interpretablescore_boxplot.py
pyCellPhenoX/plot_interpretablescore_umap.py
pyCellPhenoX/preprocessing.py
pyCellPhenoX/principalComponentAnalysis.py
pyCellPhenoX/utils/__init__.py
pyCellPhenoX/utils/balanced_sample.py
pyCellPhenoX/utils/check_indices.py
pyCellPhenoX/utils/reducedim.py
pyCellPhenoX/utils/select_num_components.py
pyCellPhenoX/utils/select_optimal_k.py
pycellphenox-1.5.1.dist-info/LICENSE
pycellphenox-1.5.1.dist-info/METADATA
pycellphenox-1.5.1.dist-info/WHEEL
pycellphenox-1.5.1.dist-info/RECORD
