Metadata-Version: 2.1
Name: pyCellPhenoX
Version: 1.5.1
Summary: An eXplainable Cell-specific machine learning method to predict clinical Phenotypes using single-cell multi-omics
Home-page: https://pyCellPhenoX.readthedocs.io/
License: MIT
Author: Jade Young
Maintainer: Revanth Krishna
Maintainer-email: revanth.krishna@cuanschutz.edu
Requires-Python: >=3.9,<4.0
Classifier: License :: OSI Approved :: MIT License
Classifier: Programming Language :: Python :: 3
Classifier: Programming Language :: Python :: 3.9
Classifier: Programming Language :: Python :: 3.10
Classifier: Programming Language :: Python :: 3.11
Classifier: Programming Language :: Python :: 3.12
Classifier: Programming Language :: Python :: 3.13
Requires-Dist: fasttreeshap (>=0.1.5,<0.2.0)
Requires-Dist: matplotlib (>=3.9.2,<4.0.0)
Requires-Dist: met-brewer (>=1.0.2,<2.0.0)
Requires-Dist: numba (>=0.54)
Requires-Dist: numpy (>=1.26,<2.0)
Requires-Dist: pandas (>=2.2.3,<3.0.0)
Requires-Dist: scikit-learn (>=1.5.2,<2.0.0)
Requires-Dist: shap (>=0.45,<0.46)
Requires-Dist: statsmodels (>=0.14.3,<0.15.0)
Requires-Dist: xgboost (>=2.1.1,<3.0.0)
Project-URL: Repository, https://github.com/fanzhanglab/pyCellPhenoX
